LICENSE
MANIFEST.in
README.md
requirements.txt
setup.py
vdw/__init__.py
vdw/models.py
vdw/signals.py
vdw.egg-info/PKG-INFO
vdw.egg-info/SOURCES.txt
vdw.egg-info/dependency_links.txt
vdw.egg-info/requires.txt
vdw.egg-info/top_level.txt
vdw/assessments/__init__.py
vdw/assessments/models.py
vdw/assessments/fixtures/assessment_categories.json
vdw/assessments/fixtures/parental_results.json
vdw/assessments/fixtures/pathogenicities.json
vdw/assessments/migrations/0001_initial.py
vdw/assessments/migrations/0002_auto__chg_field_assessment_category.py
vdw/assessments/migrations/0003_auto__add_field_assessment_notes__add_field_assessment_created__add_fi.py
vdw/assessments/migrations/0004_auto__add_assessmentcategory__add_field_assessment_assessment_category.py
vdw/assessments/migrations/0005_copy_categories.py
vdw/assessments/migrations/0006_auto__del_category__del_field_assessment_category.py
vdw/assessments/migrations/0007_auto__add_unique_assessment_user_sample_result.py
vdw/assessments/migrations/0008_load_pathogenicities.py
vdw/assessments/migrations/0009_load_assessment_categories.py
vdw/assessments/migrations/0010_load_parental_results.py
vdw/assessments/migrations/0011_add_other_assessment_category.py
vdw/assessments/migrations/0012_add_default_categories_to_existing_assessments.py
vdw/assessments/migrations/0013_auto__chg_field_assessment_assessment_category.py
vdw/assessments/migrations/__init__.py
vdw/conf/__init__.py
vdw/conf/global_settings.py
vdw/conf/local_settings.py
vdw/conf/settings.py
vdw/core/__init__.py
vdw/core/models.py
vdw/db/__init__.py
vdw/db/utils.py
vdw/genes/__init__.py
vdw/genes/managers.py
vdw/genes/models.py
vdw/genes/management/__init__.py
vdw/genes/management/commands/__init__.py
vdw/genes/management/commands/genes.py
vdw/genes/management/subcommands/__init__.py
vdw/genes/management/subcommands/load.py
vdw/genes/migrations/0001_initial.py
vdw/genes/migrations/0002_auto__add_field_geneset_published.py
vdw/genes/migrations/0003_auto.py
vdw/genes/migrations/0004_auto__chg_field_geneset_created__chg_field_geneset_modified.py
