Metadata-Version: 1.1
Name: vdw
Version: 0.4.1
Summary: Models and loader for processing, storing, and querying genetic data
Home-page: http://github.com/cbmi/varify-data-warehouse
Author: Byron Ruth
Author-email: b@devel.io
License: BSD
Keywords: vcf varify harvest orm genome
Platform: UNKNOWN
Classifier: Development Status :: 5 - Production/Stable
Classifier: License :: OSI Approved :: BSD License
Classifier: Programming Language :: Python :: 2.6
Classifier: Programming Language :: Python :: 2.7
Classifier: Framework :: Django
Classifier: Topic :: Internet :: WWW/HTTP
Classifier: Intended Audience :: Developers
Classifier: Intended Audience :: Science/Research
Classifier: Intended Audience :: Healthcare Industry
Classifier: Intended Audience :: Information Technology
